nata/__init__.py
nata/axes.py
nata/backends/__init__.py
nata/backends/osiris/__init__.py
nata/backends/osiris/hdf5.py
nata/backends/osiris/zdf.py
nata/comfort.py
nata/containers.py
nata/plots/__init__.py
nata/plots/axes.py
nata/plots/data.py
nata/plots/figure.py
nata/plots/helpers.py
nata/plots/plans.py
nata/plots/styles/dark.rc
nata/plots/styles/light.rc
nata/plots/types/__init__.py
nata/plots/types/base.py
nata/plots/types/color.py
nata/plots/types/line.py
nata/plots/types/scatter.py
nata/plugins/__init__.py
nata/plugins/grids/__init__.py
nata/plugins/grids/fft.py
nata/plugins/grids/lineout.py
nata/plugins/particles/__init__.py
nata/plugins/particles/filter.py
nata/plugins/plot/__init__.py
nata/plugins/plot/collection.py
nata/plugins/plot/grid.py
nata/plugins/plot/particle.py
nata/plugins/register.py
nata/types.py
nata/utils/__init__.py
nata/utils/array.py
nata/utils/backends.py
nata/utils/cached_property.py
nata/utils/container_tools.py
nata/utils/env.py
nata/utils/exceptions.py
nata/utils/formatting.py
nata/utils/zdf.py
nata-0.0.3.dist-info/LICENSE
nata-0.0.3.dist-info/WHEEL
nata-0.0.3.dist-info/METADATA
nata-0.0.3.dist-info/RECORD
