Metadata-Version: 2.1
Name: nata
Version: 0.0.3
Summary: Post-processing and visualization for PIC codes
Home-page: https://github.com/GoLP-IST/nata
License: MIT
Keywords: post-processing,visualization,particle-in-cell
Author: Anton Helm
Author-email: anton.helm@tecnico.ulisboa.pt
Maintainer: Anton Helm
Maintainer-email: anton.helm@tecnico.ulisboa.pt
Requires-Python: >=3.6,<4.0
Classifier: Development Status :: 3 - Alpha
Classifier: Intended Audience :: Education
Classifier: Intended Audience :: Science/Research
Classifier: License :: OSI Approved :: MIT License
Classifier: Natural Language :: English
Classifier: Operating System :: OS Independent
Classifier: Programming Language :: Python
Classifier: Programming Language :: Python :: 3
Classifier: Programming Language :: Python :: 3.6
Classifier: Programming Language :: Python :: 3.7
Classifier: Programming Language :: Python :: 3.8
Classifier: Programming Language :: Python :: 3.9
Classifier: Topic :: Scientific/Engineering :: Physics
Classifier: Topic :: Scientific/Engineering :: Visualization
Provides-Extra: docs
Provides-Extra: wiptools
Requires-Dist: dataclasses (>=0.7,<0.8); python_version >= "3.6" and python_version < "3.7"
Requires-Dist: h5py (>=2.10.0,<3.0.0)
Requires-Dist: ipywidgets (>=7.5.1,<8.0.0)
Requires-Dist: jupyterlab (>=2.1.2,<3.0.0); extra == "wiptools"
Requires-Dist: matplotlib (>=3.1.2,<4.0.0)
Requires-Dist: ndindex (>=1.3.1,<2.0.0)
Requires-Dist: numpy (>=1.18.1,<2.0.0)
Requires-Dist: recommonmark (>=0.6.0,<0.7.0); extra == "docs"
Requires-Dist: sphinx (>=3.0.3,<4.0.0); extra == "docs"
Requires-Dist: sphinx-rtd-theme (>=0.4.3,<0.5.0); extra == "docs"
Requires-Dist: typing_extensions (>=3.7.4,<4.0.0); python_version < "3.8"
Project-URL: Bug Tracker, https://github.com/GoLP-IST/nata/issues
Project-URL: Documentation, https://github.com/GoLP-IST/nata
Project-URL: Repository, https://github.com/GoLP-IST/nata
